hostchecker/__init__.py
hostchecker/__main__.py
hostchecker/hostStorage.py
hostchecker/hostingInfo.py
host_checker-1.0.3.dist-info/LICENSE
host_checker-1.0.3.dist-info/METADATA
host_checker-1.0.3.dist-info/WHEEL
host_checker-1.0.3.dist-info/top_level.txt
host_checker-1.0.3.dist-info/RECORD
