Metadata-Version: 2.1
Name: host-checker
Version: 1.0.3
Summary: Simple CLI tool to check who is hosting a website
Home-page: https://github.com/SimoneCorazza/HostChecker
License: UNKNOWN
Platform: UNKNOWN
Classifier: Programming Language :: Python :: 3
Classifier: Operating System :: OS Independent
